limin_vision/__init__.py
limin_vision/py.typed
limin_vision-0.3.0.dist-info/METADATA
limin_vision-0.3.0.dist-info/WHEEL
limin_vision-0.3.0.dist-info/top_level.txt
limin_vision-0.3.0.dist-info/RECORD
