Metadata-Version: 2.4
Name: limin-vision
Version: 0.3.0
Summary: A Python library for working with vision models.
Author-email: Titanom Solutions <infrastructure@titanom.com>
Requires-Python: >=3.10
Requires-Dist: limin==0.8.0
